mcp_clickhouse/__init__.py
mcp_clickhouse/main.py
mcp_clickhouse/mcp_env.py
mcp_clickhouse/mcp_server.py
orange_mcp_clickhouse-0.1.5.dist-info/METADATA
orange_mcp_clickhouse-0.1.5.dist-info/WHEEL
orange_mcp_clickhouse-0.1.5.dist-info/entry_points.txt
orange_mcp_clickhouse-0.1.5.dist-info/licenses/LICENSE
orange_mcp_clickhouse-0.1.5.dist-info/RECORD
